confusion_factor/__init__.py
confusion_factor/example.py
confusion_factor/histo_confusion.py
histo_confusion_factor_ijhwlee-0.0.2.dist-info/LICENSE
histo_confusion_factor_ijhwlee-0.0.2.dist-info/METADATA
histo_confusion_factor_ijhwlee-0.0.2.dist-info/WHEEL
histo_confusion_factor_ijhwlee-0.0.2.dist-info/top_level.txt
histo_confusion_factor_ijhwlee-0.0.2.dist-info/RECORD
